ghost/__init__.py
ghost/engine.py
ghost/ghost.py
ghost_word_game-0.3.11.dist-info/DESCRIPTION.rst
ghost_word_game-0.3.11.dist-info/METADATA
ghost_word_game-0.3.11.dist-info/RECORD
ghost_word_game-0.3.11.dist-info/WHEEL
ghost_word_game-0.3.11.dist-info/metadata.json
ghost_word_game-0.3.11.dist-info/top_level.txt
