Metadata-Version: 2.0
Name: ghost-word-game
Version: 0.3.11
Summary: Python engine for Ghost word game
Home-page: https://github.com/pikulet/ghost
Author: Joyce Yeo
Author-email: jycyeo@yahoo.com.sg
License: UNKNOWN
Platform: UNKNOWN
Classifier: Programming Language :: Python :: 3
Classifier: License :: OSI Approved :: MIT License
Classifier: Operating System :: OS Independent
Requires-Python: >=3.6
